{"gold":[{"date":"1404/10/07","time":"11:12","time_unix":1766907745,"symbol":"IR_GOLD_18K","name_en":"18K Gold","name":"طلای 18 عیار","price":15864100,"change_value":518100,"change_percent":3.38,"unit":"تومان"},{"date":"1404/10/07","time":"11:12","time_unix":1766907745,"symbol":"IR_GOLD_24K","name_en":"24K Gold","name":"طلای 24 عیار","price":21151900,"change_value":690700,"change_percent":3.38,"unit":"تومان"},{"date":"1404/10/07","time":"11:12","time_unix":1766907745,"symbol":"IR_GOLD_MELTED","name_en":"Melted Gold","name":"طلای آب‌شده نقدی","price":68710000,"change_value":2226000,"change_percent":3.35,"unit":"تومان"},{"date":"1404/10/07","time":"00:00","time_unix":1766867400,"symbol":"XAUUSD","name_en":"Gold Ounce","name":"انس طلا","price":4532,"change_value":0,"change_percent":0,"unit":"دلار"},{"date":"1404/10/07","time":"11:04","time_unix":1766907271,"symbol":"IR_COIN_1G","name_en":"1g Coin","name":"سکه یک گرمی","price":22200000,"change_value":400000,"change_percent":1.83,"unit":"تومان"},{"date":"1404/10/07","time":"11:07","time_unix":1766907469,"symbol":"IR_COIN_QUARTER","name_en":"Quarter Coin","name":"ربع سکه","price":53500000,"change_value":2120000,"change_percent":4.13,"unit":"تومان"},{"date":"1404/10/07","time":"11:06","time_unix":1766907412,"symbol":"IR_COIN_HALF","name_en":"Half Coin","name":"نیم سکه","price":88500000,"change_value":2310000,"change_percent":2.68,"unit":"تومان"},{"date":"1404/10/07","time":"11:12","time_unix":1766907745,"symbol":"IR_COIN_EMAMI","name_en":"Emami Coin","name":"سکه امامی","price":164510000,"change_value":5700000,"change_percent":3.59,"unit":"تومان"},{"date":"1404/10/07","time":"11:12","time_unix":1766907745,"symbol":"IR_COIN_BAHAR","name_en":"Bahar Azadi Coin","name":"سکه بهار آزادی","price":156000000,"change_value":5055000,"change_percent":3.35,"unit":"تومان"}],"currency":[{"date":"1404/10/07","time":"11:12","time_unix":1766907754,"symbol":"USDT_IRT","name_en":"Tether Dollar","name":"دلار تتر","price":142890,"change_value":6126,"change_percent":4.48,"unit":"تومان"},{"date":"1404/10/07","time":"11:12","time_unix":1766907745,"symbol":"USD","name_en":"US Dollar","name":"دلار","price":142070,"change_value":3240,"change_percent":2.33,"unit":"تومان"},{"date":"1404/10/07","time":"11:12","time_unix":1766907736,"symbol":"EUR","name_en":"Euro","name":"یورو","price":167280,"change_value":3830,"change_percent":2.34,"unit":"تومان"},{"date":"1404/10/07","time":"11:12","time_unix":1766907736,"symbol":"AED","name_en":"UAE Dirham","name":"درهم امارات","price":38699,"change_value":885,"change_percent":2.34,"unit":"تومان"},{"date":"1404/10/07","time":"11:12","time_unix":1766907736,"symbol":"GBP","name_en":"British Pound","name":"پوند","price":191720,"change_value":4390,"change_percent":2.34,"unit":"تومان"},{"date":"1404/10/07","time":"11:12","time_unix":1766907736,"symbol":"JPY","name_en":"Japanese Yen","name":"یکصد ین ژاپن","price":90750,"change_value":2076,"change_percent":2.34,"unit":"تومان"},{"date":"1404/10/07","time":"11:12","time_unix":1766907736,"symbol":"KWD","name_en":"Kuwaiti Dinar","name":"دینار کویت","price":462670,"change_value":10600,"change_percent":2.34,"unit":"تومان"},{"date":"1404/10/07","time":"11:12","time_unix":1766907736,"symbol":"AUD","name_en":"Australian Dollar","name":"دلار استرالیا","price":95380,"change_value":2180,"change_percent":2.34,"unit":"تومان"},{"date":"1404/10/07","time":"11:12","time_unix":1766907736,"symbol":"CAD","name_en":"Canadian Dollar","name":"دلار کانادا","price":103930,"change_value":2380,"change_percent":2.34,"unit":"تومان"},{"date":"1404/10/07","time":"11:11","time_unix":1766907708,"symbol":"CNY","name_en":"Chinese Yuan","name":"یوآن چین","price":20280,"change_value":460,"change_percent":2.32,"unit":"تومان"},{"date":"1404/10/07","time":"11:00","time_unix":1766907046,"symbol":"TRY","name_en":"Turkish Lira","name":"لیر ترکیه","price":3310,"change_value":80,"change_percent":2.48,"unit":"تومان"},{"date":"1404/10/07","time":"11:12","time_unix":1766907736,"symbol":"SAR","name_en":"Saudi Riyal","name":"ریال عربستان","price":37888,"change_value":866,"change_percent":2.34,"unit":"تومان"},{"date":"1404/10/07","time":"11:12","time_unix":1766907736,"symbol":"CHF","name_en":"Swiss Franc","name":"فرانک سوئیس","price":180050,"change_value":4120,"change_percent":2.34,"unit":"تومان"},{"date":"1404/10/07","time":"11:11","time_unix":1766907708,"symbol":"INR","name_en":"Indian Rupee","name":"روپیه هند","price":1583,"change_value":36,"change_percent":2.33,"unit":"تومان"},{"date":"1404/10/07","time":"11:12","time_unix":1766907730,"symbol":"PKR","name_en":"Pakistani Rupee","name":"روپیه پاکستان","price":509,"change_value":11,"change_percent":2.35,"unit":"تومان"},{"date":"1404/10/07","time":"11:12","time_unix":1766907736,"symbol":"IQD","name_en":"Iraqi Dinar","name":"دینار عراق","price":110,"change_value":2,"change_percent":2.31,"unit":"تومان"},{"date":"1404/10/07","time":"11:00","time_unix":1766907046,"symbol":"SYP","name_en":"Syrian Lira","name":"لیر سوریه","price":12,"change_value":0,"change_percent":2.4,"unit":"تومان"},{"date":"1404/10/07","time":"11:11","time_unix":1766907707,"symbol":"SEK","name_en":"Swedish Krona","name":"کرون سوئد","price":15530,"change_value":360,"change_percent":2.37,"unit":"تومان"},{"date":"1404/10/07","time":"11:12","time_unix":1766907736,"symbol":"QAR","name_en":"Qatari Riyal","name":"ریال قطر","price":39040,"change_value":920,"change_percent":2.41,"unit":"تومان"},{"date":"1404/10/07","time":"11:12","time_unix":1766907736,"symbol":"OMR","name_en":"Omani Rial","name":"ریال عمان","price":369050,"change_value":8440,"change_percent":2.34,"unit":"تومان"},{"date":"1404/10/07","time":"11:12","time_unix":1766907736,"symbol":"BHD","name_en":"Bahraini Dinar","name":"دینار بحرین","price":376507,"change_value":8620,"change_percent":2.34,"unit":"تومان"},{"date":"1404/10/07","time":"11:12","time_unix":1766907733,"symbol":"AFN","name_en":"Afghan Afghani","name":"افغانی","price":2149,"change_value":50,"change_percent":2.38,"unit":"تومان"},{"date":"1404/10/07","time":"11:11","time_unix":1766907711,"symbol":"MYR","name_en":"Malaysian Ringgit","name":"رینگیت مالزی","price":35120,"change_value":810,"change_percent":2.36,"unit":"تومان"},{"date":"1404/10/07","time":"11:12","time_unix":1766907736,"symbol":"THB","name_en":"Thai Baht","name":"بات تایلند","price":4575,"change_value":104,"change_percent":2.33,"unit":"تومان"},{"date":"1404/10/07","time":"11:12","time_unix":1766907729,"symbol":"RUB","name_en":"Russian Ruble","name":"روبل روسیه","price":1832,"change_value":42,"change_percent":2.35,"unit":"تومان"},{"date":"1404/10/07","time":"11:12","time_unix":1766907736,"symbol":"AZN","name_en":"Azerbaijani Manat","name":"منات آذربایجان","price":83630,"change_value":1920,"change_percent":2.35,"unit":"تومان"},{"date":"1404/10/07","time":"11:11","time_unix":1766907708,"symbol":"AMD","name_en":"Armenian Dram","name":"درام ارمنستان","price":373,"change_value":9,"change_percent":2.47,"unit":"تومان"},{"date":"1404/10/07","time":"11:12","time_unix":1766907733,"symbol":"GEL","name_en":"Georgian Lari","name":"لاری گرجستان","price":52840,"change_value":1220,"change_percent":2.36,"unit":"تومان"}],"cryptocurrency":[{"date":"1404/10/07","time":"11:12","time_unix":1766907754,"symbol":"BTC","name_en":"Bitcoin","name":"بیت‌کوین","price":"87601.81","change_percent":-0.03,"market_cap":1749206630060,"unit":"دلار","description":"اولین و معروف‌ترین رمزارز جهان، با ارزش بازار بالا و پذیرش گسترده به عنوان طلای دیجیتال"},{"date":"1404/10/07","time":"11:12","time_unix":1766907754,"symbol":"ETH","name_en":"Ethereum","name":"اتریوم","price":"2935.82","change_percent":-0.02,"market_cap":354284190618,"unit":"دلار","description":"پلتفرم پیشرو برای قراردادهای هوشمند و برنامه‌های غیرمتمرکز (DApps)، با اکوسیستمی غنی"},{"date":"1404/10/07","time":"11:12","time_unix":1766907754,"symbol":"USDT","name_en":"Tether","name":"تتر","price":"0.9992","change_percent":-0.01,"market_cap":186671796728,"unit":"دلار","description":"استیبل‌کوین محبوب با ارزش ثابت برابر ۱ دلار آمریکا، مناسب برای حفظ ارزش دارایی‌ها"},{"date":"1404/10/07","time":"11:12","time_unix":1766907754,"symbol":"XRP","name_en":"XRP","name":"ایکس‌آر‌پی","price":"1.87993","change_percent":1.66,"market_cap":113568045577,"unit":"دلار","description":"رمزارزی برای پرداخت‌های سریع و کم‌هزینه بین‌المللی، با تمرکز بر همکاری با مؤسسات مالی"},{"date":"1404/10/07","time":"11:12","time_unix":1766907754,"symbol":"BNB","name_en":"BNB","name":"بی‌ان‌بی","price":"841.2715","change_percent":-0.02,"market_cap":116075636668,"unit":"دلار","description":"توکن بومی صرافی بایننس، با کاربرد در پرداخت کارمزدها و مشارکت در اکوسیستم بایننس"},{"date":"1404/10/07","time":"11:12","time_unix":1766907754,"symbol":"SOL","name_en":"Solana","name":"سولانا","price":"123.93","change_percent":0.85,"market_cap":69762507970,"unit":"دلار","description":"بلاک‌چینی فوق‌سریع و کم‌هزینه، مناسب برای برنامه‌های غیرمتمرکز و توکن‌های NFT"},{"date":"1404/10/07","time":"11:12","time_unix":1766907754,"symbol":"USDC","name_en":"USD Coin","name":"یواس‌دی کوین","price":"0.9971","change_percent":0.16,"market_cap":76396697495,"unit":"دلار","description":"استیبل‌کوینی معتبر با پشتوانه دلار آمریکا، تحت نظارت شرکت‌های مالی معتبر"},{"date":"1404/10/07","time":"11:12","time_unix":1766907754,"symbol":"TRX","name_en":"TRON","name":"ترون","price":"0.28428","change_percent":1.63,"market_cap":26848875413,"unit":"دلار","description":"بلاک‌چینی برای محتوا و سرگرمی، با تمرکز بر پرداخت‌های دیجیتال و تولید محتوا"},{"date":"1404/10/07","time":"11:12","time_unix":1766907754,"symbol":"DOGE","name_en":"Dogecoin","name":"دوج‌کوین","price":"0.1238","change_percent":0.63,"market_cap":20856144289,"unit":"دلار","description":"میم‌کوینی محبوب با جامعه‌ای فعال، مناسب برای پرداخت‌های خرد و فعالیت‌های اجتماعی"},{"date":"1404/10/07","time":"11:12","time_unix":1766907754,"symbol":"ADA","name_en":"Cardano","name":"کاردانو","price":"0.3747","change_percent":6.42,"market_cap":13451870376,"unit":"دلار","description":"پلتفرمی امن و مقیاس‌پذیر برای قراردادهای هوشمند، با رویکردی علمی و تحقیق‌محور"},{"date":"1404/10/07","time":"11:12","time_unix":1766907754,"symbol":"LINK","name_en":"Chainlink","name":"چین‌لینک","price":"12.4054","change_percent":1.45,"market_cap":8799053799,"unit":"دلار","description":"پروژه‌ای برای اتصال داده‌های دنیای واقعی به بلاک‌چین، ضروری برای قراردادهای هوشمند"},{"date":"1404/10/07","time":"11:12","time_unix":1766907754,"symbol":"XLM","name_en":"Stellar","name":"استلار","price":"0.22427","change_percent":4.41,"market_cap":7252712654,"unit":"دلار","description":"شبکه‌ای برای پرداخت‌های بین‌المللی ارزان و سریع، با تمرکز بر بانکداری بدون مرز"},{"date":"1404/10/07","time":"11:12","time_unix":1766907754,"symbol":"AVAX","name_en":"Avalanche","name":"آوالانچ","price":"12.74","change_percent":2,"market_cap":5486621340,"unit":"دلار","description":"بلاک‌چینی سریع و مقیاس‌پذیر، رقیبی برای اتریوم و سولانا در حوزه قراردادهای هوشمند"},{"date":"1404/10/07","time":"11:12","time_unix":1766907754,"symbol":"SHIB","name_en":"Shiba Inu","name":"شیبا اینو","price":"0.00000733","change_percent":2.95,"market_cap":4734461,"unit":"دلار","description":"توکنی محبوب با الهام از دوج‌کوین، با اکوسیستمی در حال رشد و جذابیت برای سرمایه‌گذاران خرد"},{"date":"1404/10/07","time":"11:12","time_unix":1766907754,"symbol":"LTC","name_en":"Litecoin","name":"لایت‌کوین","price":"79.72","change_percent":3.06,"market_cap":6114844385,"unit":"دلار","description":"یکی از قدیمی‌ترین رمزارزها، با تراکنش‌های سریع‌تر و کارمزد کمتر نسبت به بیت‌کوین"},{"date":"1404/10/07","time":"11:12","time_unix":1766907754,"symbol":"DOT","name_en":"Polkadot","name":"پولکادات","price":"1.899","change_percent":7.9,"market_cap":3120195110,"unit":"دلار","description":"پروژه‌ای برای اتصال بلاک‌چین‌های مختلف و ایجاد یک شبکه یکپارچه و تعاملی"},{"date":"1404/10/07","time":"11:12","time_unix":1766907754,"symbol":"UNI","name_en":"Uniswap","name":"یونی‌سواپ","price":"6.3369","change_percent":6.72,"market_cap":4611689592,"unit":"دلار","description":"توکن حاکمیتی بزرگ‌ترین صرافی غیرمتمرکز (DEX)، پیشرو در حوزه دیفای (DeFi)"},{"date":"1404/10/07","time":"11:12","time_unix":1766907754,"symbol":"ATOM","name_en":"Cosmos","name":"کازماس","price":"2.1","change_percent":2.94,"market_cap":1017452892,"unit":"دلار","description":"پروژه‌ای برای ایجاد اینترنت بلاک‌چین‌ها، با هدف ارتباط بین زنجیره‌های مختلف"},{"date":"1404/10/07","time":"11:12","time_unix":1766907754,"symbol":"FIL","name_en":"Filecoin","name":"فایل‌کوین","price":"1.3651","change_percent":9.32,"market_cap":993290086,"unit":"دلار","description":"شبکه‌ای غیرمتمرکز برای ذخیره‌سازی داده‌ها، با امکان کسب درآمد از فضای ذخیره‌سازی"}]}