{"gold":[{"date":"1404/10/15","time":"19:59","time_unix":1767630594,"symbol":"IR_GOLD_18K","name_en":"18K Gold","name":"طلای 18 عیار","price":15684000,"change_value":959900,"change_percent":6.52,"unit":"تومان"},{"date":"1404/10/15","time":"19:59","time_unix":1767630594,"symbol":"IR_GOLD_24K","name_en":"24K Gold","name":"طلای 24 عیار","price":20911800,"change_value":1279800,"change_percent":6.52,"unit":"تومان"},{"date":"1404/10/15","time":"19:59","time_unix":1767630596,"symbol":"IR_GOLD_MELTED","name_en":"Melted Gold","name":"طلای آب‌شده نقدی","price":67940000,"change_value":4150000,"change_percent":6.51,"unit":"تومان"},{"date":"1404/10/15","time":"21:19","time_unix":1767635358,"symbol":"XAUUSD","name_en":"Gold Ounce","name":"انس طلا","price":4441,"change_value":110,"change_percent":2.56,"unit":"دلار"},{"date":"1404/10/15","time":"15:42","time_unix":1767615154,"symbol":"IR_COIN_1G","name_en":"1g Coin","name":"سکه یک گرمی","price":22400000,"change_value":400000,"change_percent":1.82,"unit":"تومان"},{"date":"1404/10/15","time":"18:27","time_unix":1767625045,"symbol":"IR_COIN_QUARTER","name_en":"Quarter Coin","name":"ربع سکه","price":51520000,"change_value":1520000,"change_percent":3.04,"unit":"تومان"},{"date":"1404/10/15","time":"17:43","time_unix":1767622419,"symbol":"IR_COIN_HALF","name_en":"Half Coin","name":"نیم سکه","price":85020000,"change_value":2020000,"change_percent":2.43,"unit":"تومان"},{"date":"1404/10/15","time":"19:59","time_unix":1767630596,"symbol":"IR_COIN_EMAMI","name_en":"Emami Coin","name":"سکه امامی","price":160010000,"change_value":6530000,"change_percent":4.25,"unit":"تومان"},{"date":"1404/10/15","time":"19:59","time_unix":1767630596,"symbol":"IR_COIN_BAHAR","name_en":"Bahar Azadi Coin","name":"سکه بهار آزادی","price":152865000,"change_value":6985000,"change_percent":4.79,"unit":"تومان"}],"currency":[{"date":"1404/10/15","time":"21:19","time_unix":1767635381,"symbol":"USDT_IRT","name_en":"Tether Dollar","name":"دلار تتر","price":144290,"change_value":5442,"change_percent":3.92,"unit":"تومان"},{"date":"1404/10/15","time":"19:59","time_unix":1767630596,"symbol":"USD","name_en":"US Dollar","name":"دلار","price":143760,"change_value":5820,"change_percent":4.22,"unit":"تومان"},{"date":"1404/10/15","time":"19:59","time_unix":1767630594,"symbol":"EUR","name_en":"Euro","name":"یورو","price":168410,"change_value":6640,"change_percent":4.1,"unit":"تومان"},{"date":"1404/10/15","time":"19:59","time_unix":1767630594,"symbol":"AED","name_en":"UAE Dirham","name":"درهم امارات","price":39171,"change_value":1592,"change_percent":4.24,"unit":"تومان"},{"date":"1404/10/15","time":"19:59","time_unix":1767630594,"symbol":"GBP","name_en":"British Pound","name":"پوند","price":194310,"change_value":8600,"change_percent":4.63,"unit":"تومان"},{"date":"1404/10/15","time":"19:59","time_unix":1767630595,"symbol":"JPY","name_en":"Japanese Yen","name":"یکصد ین ژاپن","price":91898,"change_value":3883,"change_percent":4.41,"unit":"تومان"},{"date":"1404/10/15","time":"19:59","time_unix":1767630595,"symbol":"KWD","name_en":"Kuwaiti Dinar","name":"دینار کویت","price":468460,"change_value":19190,"change_percent":4.27,"unit":"تومان"},{"date":"1404/10/15","time":"19:59","time_unix":1767630595,"symbol":"AUD","name_en":"Australian Dollar","name":"دلار استرالیا","price":96530,"change_value":4150,"change_percent":4.49,"unit":"تومان"},{"date":"1404/10/15","time":"19:59","time_unix":1767630595,"symbol":"CAD","name_en":"Canadian Dollar","name":"دلار کانادا","price":104550,"change_value":4030,"change_percent":4.01,"unit":"تومان"},{"date":"1404/10/15","time":"19:57","time_unix":1767630458,"symbol":"CNY","name_en":"Chinese Yuan","name":"یوآن چین","price":20580,"change_value":840,"change_percent":4.26,"unit":"تومان"},{"date":"1404/10/15","time":"19:57","time_unix":1767630458,"symbol":"TRY","name_en":"Turkish Lira","name":"لیر ترکیه","price":3340,"change_value":140,"change_percent":4.38,"unit":"تومان"},{"date":"1404/10/15","time":"19:59","time_unix":1767630595,"symbol":"SAR","name_en":"Saudi Riyal","name":"ریال عربستان","price":38389,"change_value":1546,"change_percent":4.2,"unit":"تومان"},{"date":"1404/10/15","time":"19:59","time_unix":1767630595,"symbol":"CHF","name_en":"Swiss Franc","name":"فرانک سوئیس","price":181450,"change_value":7170,"change_percent":4.11,"unit":"تومان"},{"date":"1404/10/15","time":"19:57","time_unix":1767630458,"symbol":"INR","name_en":"Indian Rupee","name":"روپیه هند","price":1596,"change_value":62,"change_percent":4.04,"unit":"تومان"},{"date":"1404/10/15","time":"19:59","time_unix":1767630595,"symbol":"PKR","name_en":"Pakistani Rupee","name":"روپیه پاکستان","price":514,"change_value":21,"change_percent":4.4,"unit":"تومان"},{"date":"1404/10/15","time":"19:57","time_unix":1767630458,"symbol":"IQD","name_en":"Iraqi Dinar","name":"دینار عراق","price":111,"change_value":6,"change_percent":6.07,"unit":"تومان"},{"date":"1404/10/15","time":"19:59","time_unix":1767630595,"symbol":"SYP","name_en":"Syrian Lira","name":"لیر سوریه","price":1300,"change_value":1288,"change_percent":10391.1,"unit":"تومان"},{"date":"1404/10/15","time":"19:59","time_unix":1767630595,"symbol":"SEK","name_en":"Swedish Krona","name":"کرون سوئد","price":15670,"change_value":680,"change_percent":4.54,"unit":"تومان"},{"date":"1404/10/15","time":"19:59","time_unix":1767630595,"symbol":"QAR","name_en":"Qatari Riyal","name":"ریال قطر","price":39410,"change_value":1660,"change_percent":4.4,"unit":"تومان"},{"date":"1404/10/15","time":"19:59","time_unix":1767630595,"symbol":"OMR","name_en":"Omani Rial","name":"ریال عمان","price":373540,"change_value":15050,"change_percent":4.2,"unit":"تومان"},{"date":"1404/10/15","time":"19:59","time_unix":1767630595,"symbol":"BHD","name_en":"Bahraini Dinar","name":"دینار بحرین","price":381420,"change_value":15370,"change_percent":4.2,"unit":"تومان"},{"date":"1404/10/15","time":"19:59","time_unix":1767630558,"symbol":"AFN","name_en":"Afghan Afghani","name":"افغانی","price":2180,"change_value":43,"change_percent":2.01,"unit":"تومان"},{"date":"1404/10/15","time":"19:59","time_unix":1767630595,"symbol":"MYR","name_en":"Malaysian Ringgit","name":"رینگیت مالزی","price":35340,"change_value":1270,"change_percent":3.73,"unit":"تومان"},{"date":"1404/10/15","time":"19:59","time_unix":1767630595,"symbol":"THB","name_en":"Thai Baht","name":"بات تایلند","price":4588,"change_value":213,"change_percent":4.87,"unit":"تومان"},{"date":"1404/10/15","time":"19:59","time_unix":1767630595,"symbol":"RUB","name_en":"Russian Ruble","name":"روبل روسیه","price":1779,"change_value":60,"change_percent":3.49,"unit":"تومان"},{"date":"1404/10/15","time":"19:59","time_unix":1767630595,"symbol":"AZN","name_en":"Azerbaijani Manat","name":"منات آذربایجان","price":84650,"change_value":3420,"change_percent":4.21,"unit":"تومان"},{"date":"1404/10/15","time":"19:51","time_unix":1767630100,"symbol":"AMD","name_en":"Armenian Dram","name":"درام ارمنستان","price":357,"change_value":-11,"change_percent":-3.08,"unit":"تومان"},{"date":"1404/10/15","time":"19:59","time_unix":1767630595,"symbol":"GEL","name_en":"Georgian Lari","name":"لاری گرجستان","price":53460,"change_value":2170,"change_percent":4.23,"unit":"تومان"}],"cryptocurrency":[{"date":"1404/10/15","time":"21:19","time_unix":1767635381,"symbol":"BTC","name_en":"Bitcoin","name":"بیت‌کوین","price":"93629.7","change_percent":2.61,"market_cap":1874338365730,"unit":"دلار","description":"اولین و معروف‌ترین رمزارز جهان، با ارزش بازار بالا و پذیرش گسترده به عنوان طلای دیجیتال"},{"date":"1404/10/15","time":"21:19","time_unix":1767635381,"symbol":"ETH","name_en":"Ethereum","name":"اتریوم","price":"3185.06","change_percent":1.28,"market_cap":385348010530,"unit":"دلار","description":"پلتفرم پیشرو برای قراردادهای هوشمند و برنامه‌های غیرمتمرکز (DApps)، با اکوسیستمی غنی"},{"date":"1404/10/15","time":"21:19","time_unix":1767635381,"symbol":"USDT","name_en":"Tether","name":"تتر","price":"0.9998","change_percent":0.03,"market_cap":187076474721,"unit":"دلار","description":"استیبل‌کوین محبوب با ارزش ثابت برابر ۱ دلار آمریکا، مناسب برای حفظ ارزش دارایی‌ها"},{"date":"1404/10/15","time":"21:19","time_unix":1767635381,"symbol":"XRP","name_en":"XRP","name":"ایکس‌آر‌پی","price":"2.18105","change_percent":3.92,"market_cap":133096754347,"unit":"دلار","description":"رمزارزی برای پرداخت‌های سریع و کم‌هزینه بین‌المللی، با تمرکز بر همکاری با مؤسسات مالی"},{"date":"1404/10/15","time":"21:19","time_unix":1767635381,"symbol":"BNB","name_en":"BNB","name":"بی‌ان‌بی","price":"902.6646","change_percent":-0.25,"market_cap":124572409411,"unit":"دلار","description":"توکن بومی صرافی بایننس، با کاربرد در پرداخت کارمزدها و مشارکت در اکوسیستم بایننس"},{"date":"1404/10/15","time":"21:19","time_unix":1767635381,"symbol":"SOL","name_en":"Solana","name":"سولانا","price":"134.76","change_percent":-0.29,"market_cap":76467228973,"unit":"دلار","description":"بلاک‌چینی فوق‌سریع و کم‌هزینه، مناسب برای برنامه‌های غیرمتمرکز و توکن‌های NFT"},{"date":"1404/10/15","time":"21:19","time_unix":1767635381,"symbol":"USDC","name_en":"USD Coin","name":"یواس‌دی کوین","price":"1","change_percent":0,"market_cap":75550148173,"unit":"دلار","description":"استیبل‌کوینی معتبر با پشتوانه دلار آمریکا، تحت نظارت شرکت‌های مالی معتبر"},{"date":"1404/10/15","time":"21:19","time_unix":1767635381,"symbol":"TRX","name_en":"TRON","name":"ترون","price":"0.29326","change_percent":-0.87,"market_cap":27665030413,"unit":"دلار","description":"بلاک‌چینی برای محتوا و سرگرمی، با تمرکز بر پرداخت‌های دیجیتال و تولید محتوا"},{"date":"1404/10/15","time":"21:19","time_unix":1767635381,"symbol":"DOGE","name_en":"Dogecoin","name":"دوج‌کوین","price":"0.14942","change_percent":-1.81,"market_cap":25393871234,"unit":"دلار","description":"میم‌کوینی محبوب با جامعه‌ای فعال، مناسب برای پرداخت‌های خرد و فعالیت‌های اجتماعی"},{"date":"1404/10/15","time":"21:19","time_unix":1767635381,"symbol":"ADA","name_en":"Cardano","name":"کاردانو","price":"0.4076","change_percent":0.89,"market_cap":14744934088,"unit":"دلار","description":"پلتفرمی امن و مقیاس‌پذیر برای قراردادهای هوشمند، با رویکردی علمی و تحقیق‌محور"},{"date":"1404/10/15","time":"21:19","time_unix":1767635381,"symbol":"LINK","name_en":"Chainlink","name":"چین‌لینک","price":"13.6194","change_percent":0.87,"market_cap":9691170180,"unit":"دلار","description":"پروژه‌ای برای اتصال داده‌های دنیای واقعی به بلاک‌چین، ضروری برای قراردادهای هوشمند"},{"date":"1404/10/15","time":"21:19","time_unix":1767635381,"symbol":"XLM","name_en":"Stellar","name":"استلار","price":"0.23534","change_percent":0.43,"market_cap":7654454146,"unit":"دلار","description":"شبکه‌ای برای پرداخت‌های بین‌المللی ارزان و سریع، با تمرکز بر بانکداری بدون مرز"},{"date":"1404/10/15","time":"21:19","time_unix":1767635381,"symbol":"AVAX","name_en":"Avalanche","name":"آوالانچ","price":"14","change_percent":-0.14,"market_cap":6065040339,"unit":"دلار","description":"بلاک‌چینی سریع و مقیاس‌پذیر، رقیبی برای اتریوم و سولانا در حوزه قراردادهای هوشمند"},{"date":"1404/10/15","time":"21:19","time_unix":1767635381,"symbol":"SHIB","name_en":"Shiba Inu","name":"شیبا اینو","price":"0.00000937","change_percent":0.75,"market_cap":6744018,"unit":"دلار","description":"توکنی محبوب با الهام از دوج‌کوین، با اکوسیستمی در حال رشد و جذابیت برای سرمایه‌گذاران خرد"},{"date":"1404/10/15","time":"21:19","time_unix":1767635381,"symbol":"LTC","name_en":"Litecoin","name":"لایت‌کوین","price":"82.1","change_percent":-0.97,"market_cap":6347276981,"unit":"دلار","description":"یکی از قدیمی‌ترین رمزارزها، با تراکنش‌های سریع‌تر و کارمزد کمتر نسبت به بیت‌کوین"},{"date":"1404/10/15","time":"21:19","time_unix":1767635381,"symbol":"DOT","name_en":"Polkadot","name":"پولکادات","price":"2.19","change_percent":0.92,"market_cap":3614338818,"unit":"دلار","description":"پروژه‌ای برای اتصال بلاک‌چین‌های مختلف و ایجاد یک شبکه یکپارچه و تعاملی"},{"date":"1404/10/15","time":"21:19","time_unix":1767635381,"symbol":"UNI","name_en":"Uniswap","name":"یونی‌سواپ","price":"5.7419","change_percent":-3.06,"market_cap":3695885105,"unit":"دلار","description":"توکن حاکمیتی بزرگ‌ترین صرافی غیرمتمرکز (DEX)، پیشرو در حوزه دیفای (DeFi)"},{"date":"1404/10/15","time":"21:19","time_unix":1767635381,"symbol":"ATOM","name_en":"Cosmos","name":"کازماس","price":"2.36","change_percent":1.72,"market_cap":1140182681,"unit":"دلار","description":"پروژه‌ای برای ایجاد اینترنت بلاک‌چین‌ها، با هدف ارتباط بین زنجیره‌های مختلف"},{"date":"1404/10/15","time":"21:19","time_unix":1767635381,"symbol":"FIL","name_en":"Filecoin","name":"فایل‌کوین","price":"1.602","change_percent":7.09,"market_cap":1189037516,"unit":"دلار","description":"شبکه‌ای غیرمتمرکز برای ذخیره‌سازی داده‌ها، با امکان کسب درآمد از فضای ذخیره‌سازی"}]}